parallelkdepy/__init__.py
parallelkdepy/_version.py
parallelkdepy/core.py
parallelkdepy/juliapkg.json
parallelkdepy/wrapper.py
parallelkdepy-1.0.0.dist-info/METADATA
parallelkdepy-1.0.0.dist-info/WHEEL
parallelkdepy-1.0.0.dist-info/licenses/LICENSE
parallelkdepy-1.0.0.dist-info/RECORD
