Metadata-Version: 2.4
Name: parallelkdepy
Version: 1.0.0
Summary: Python wrapper of ParallelKDE.jl
License: MIT
License-File: LICENSE
Author: Christian Sustay
Author-email: christian.sustay@tum.de
Requires-Python: >=3.11,<4.0
Classifier: License :: OSI Approved :: MIT License
Classifier: Programming Language :: Python :: 3
Classifier: Programming Language :: Python :: 3.11
Classifier: Programming Language :: Python :: 3.12
Classifier: Programming Language :: Python :: 3.13
Classifier: Programming Language :: Python :: 3.14
Requires-Dist: juliacall (>=0.9,<0.10)
Requires-Dist: numpy (>=2.0,<3.0)
Project-URL: Documentation, https://chrissm23.github.io/ParallelKDEpy
Project-URL: Homepage, https://github.com/chrissm23/ParallelKDEpy
Project-URL: Repository, https://github.com/chrissm23/ParallelKDEpy
